{
  "project_info": {
    "project_number": "109496741072",
    "project_id": "ex88firebasestoragehue",
    "storage_bucket": "ex88firebasestoragehue.appspot.com"
  },
  "client": [
    {
      "client_info": {
        "mobilesdk_app_id": "1:109496741072:android:e56ae0ae16ca48e98242d5",
        "android_client_info": {
          "package_name": "com.ch96.ex88firebasestorage"
        }
      },
      "oauth_client": [
        {
          "client_id": "109496741072-db5bg4on3ch1us6sb3odlsvcil2rkknp.apps.googleusercontent.com",
          "client_type": 3
        }
      ],
      "api_key": [
        {
          "current_key": "AIzaSyDsmCBZjRnrl40fr4ZGcmTB2BsxB1Vo52I"
        }
      ],
      "services": {
        "appinvite_service": {
          "other_platform_oauth_client": [
            {
              "client_id": "109496741072-db5bg4on3ch1us6sb3odlsvcil2rkknp.apps.googleusercontent.com",
              "client_type": 3
            }
          ]
        }
      }
    }
  ],
  "configuration_version": "1"
}